amino/__init__.py
amino/client.py
amino/community.py
amino/media.py
amino/abstract/__init__.py
amino/abstract/base.py
amino/lib/__init__.py
amino/lib/util/__init__.py
amino/lib/util/exceptions.py
amino/lib/util/helpers.py
aminoacids-0.1.1.dist-info/LICENCE
aminoacids-0.1.1.dist-info/METADATA
aminoacids-0.1.1.dist-info/WHEEL
aminoacids-0.1.1.dist-info/top_level.txt
aminoacids-0.1.1.dist-info/RECORD
