Metadata-Version: 2.1
Name: aminoacids
Version: 0.1.1
Summary: Unofficial python wrapper for the Amino web api
Home-page: https://github.com/basswaver/AminoAcids
Author: Zero
Author-email: dakoolstwunn@gmail.com
License: GPLv3
Download-URL: https://github.com/basswaver/AminoAcids/tarball/master
Keywords: amino,amino-bot,bot,reverse-engineering,api,http-api,python,python3,python3.x,unofficial
Platform: UNKNOWN
Classifier: Intended Audience :: Developers
Classifier: Programming Language :: Python :: 3
Requires-Dist: requests
